clearviewai/__init__.py
clearviewai/generic/__init__.py
clearviewai/generic/processing/__init__.py
clearviewai/generic/processing/learning_rate_scheduler.py
clearviewai/primary/__init__.py
clearviewai/primary/architectures/__init__.py
clearviewai/primary/architectures/fcheadnet.py
clearviewai/primary/architectures/lenet.py
clearviewai/primary/architectures/min_vgg.py
clearviewai/primary/architectures/perceptron.py
clearviewai/primary/architectures/shallow_cnn.py
clearviewai/primary/config/__init__.py
clearviewai/primary/config/constants.py
clearviewai/primary/processing/__init__.py
clearviewai/primary/processing/aspectresize.py
clearviewai/primary/processing/image_loader.py
clearviewai/primary/processing/monitor.py
clearviewai/primary/processing/simple_processor.py
clearviewai/primary/serialize/__init__.py
clearviewai/primary/serialize/hd5f_writer.py
clearviewai/primary/testing/__init__.py
clearviewai/primary/testing/model_test.py
clearviewai/primary/training/__init__.py
clearviewai/primary/training/train_model.py
clearviewai/primary/utils/__init__.py
clearviewai/primary/utils/utils.py
clearviewai-0.0.2.dist-info/METADATA
clearviewai-0.0.2.dist-info/WHEEL
clearviewai-0.0.2.dist-info/top_level.txt
clearviewai-0.0.2.dist-info/RECORD
