Metadata-Version: 2.1
Name: clearviewai
Version: 0.0.2
Summary: deep learning for computer vision library
Home-page: UNKNOWN
Author: clearviewai
Author-email: christopher.dzuwa@gmail.com
License: UNKNOWN
Platform: UNKNOWN
Classifier: Programming Language :: Python :: 3
Classifier: License :: OSI Approved :: MIT License
Classifier: Operating System :: OS Independent
